rkt_config_lib/Config.py
rkt_config_lib/__init__.py
rkt_config_lib-1.4.0.dist-info/LICENSE
rkt_config_lib-1.4.0.dist-info/METADATA
rkt_config_lib-1.4.0.dist-info/WHEEL
rkt_config_lib-1.4.0.dist-info/top_level.txt
rkt_config_lib-1.4.0.dist-info/RECORD
